takpy-0.8.0.dist-info/METADATA
takpy-0.8.0.dist-info/WHEEL
takpy/__init__.py
takpy/__init__.pyi
takpy/py.typed
takpy/takpy.cp311-win_amd64.pyd
takpy-0.8.0.dist-info/RECORD
